jcl_datalist/__init__.py
jcl_datalist/_version.py
jcl_datalist/clusterhandler.py
jcl_datalist/config.py
jcl_datalist/dashboardhandler.py
jcl_datalist/labextension.yaml
jcl_datalist/manager.py
jcl_datalist/tests/__init__.py
jcl_datalist/tests/test_manager.py
jcl_datalist-0.0.2.data/data/etc/jupyter/jupyter_notebook_config.d/dask_labextension.json
jcl_datalist-0.0.2.data/data/etc/jupyter/jupyter_server_config.d/dask_labextension.json
jcl_datalist-0.0.2.data/data/share/jupyter/labextensions/jcl-datalist/package.json
jcl_datalist-0.0.2.data/data/share/jupyter/labextensions/jcl-datalist/schemas/jcl-datalist/package.json.orig
jcl_datalist-0.0.2.data/data/share/jupyter/labextensions/jcl-datalist/schemas/jcl-datalist/plugin.json
jcl_datalist-0.0.2.data/data/share/jupyter/labextensions/jcl-datalist/static/420.11be1919e3def5c5c41a.js
jcl_datalist-0.0.2.data/data/share/jupyter/labextensions/jcl-datalist/static/remoteEntry.c66e609ce7c3a016fd17.js
jcl_datalist-0.0.2.data/data/share/jupyter/labextensions/jcl-datalist/static/style.js
jcl_datalist-0.0.2.data/data/share/jupyter/labextensions/jcl-datalist/static/third-party-licenses.json
jcl_datalist-0.0.2.data/data/share/jupyter/labextensions/jcl-datalist/install.json
jcl_datalist-0.0.2.dist-info/METADATA
jcl_datalist-0.0.2.dist-info/WHEEL
jcl_datalist-0.0.2.dist-info/licenses/LICENSE
jcl_datalist-0.0.2.dist-info/RECORD
