Metadata-Version: 2.3
Name: jcl_datalist
Version: 0.0.2
Dynamic: Keywords
Summary: A JupyterLab extension for Dask.
Project-URL: Homepage, https://github.com/dask/dask-labextension
Project-URL: Bug Tracker, https://github.com/dask/dask-labextension/issues
Project-URL: Repository, https://github.com/dask/dask-labextension
Author: Ian Rose, Matt Rocklin, Jacob Tomlinson
License: Copyright (c) 2016, Project Jupyter Contributors and Anaconda Inc.
License-File: LICENSE
Classifier: Framework :: Jupyter
Classifier: License :: OSI Approved :: BSD License
Classifier: Programming Language :: Python
Classifier: Programming Language :: Python :: 3
Classifier: Programming Language :: Python :: 3.8
Classifier: Programming Language :: Python :: 3.9
Classifier: Programming Language :: Python :: 3.10
Classifier: Programming Language :: Python :: 3.11
Requires-Python: >=3.8
Requires-Dist: bokeh!=2.0.0,>=1.0.0
Requires-Dist: distributed>=1.24.1
Requires-Dist: jupyter-server-proxy>=1.3.2
Requires-Dist: jupyterlab<5,>=4.0.0
Provides-Extra: test
Requires-Dist: black; extra == 'test'
Requires-Dist: flake8; extra == 'test'
Requires-Dist: pytest; extra == 'test'
Requires-Dist: pytest-cov; extra == 'test'
Requires-Dist: pytest-html; extra == 'test'
